mono_dense_keras/__init__.py
mono_dense_keras/_modidx.py
mono_dense_keras/experiments.py
mono_dense_keras/helpers.py
mono_dense_keras/_components/__init__.py
mono_dense_keras/_components/mono_dense_layer.py
mono_dense_keras-0.1.1.dist-info/licenses/LICENSE
mono_dense_keras-0.1.1.dist-info/METADATA
mono_dense_keras-0.1.1.dist-info/WHEEL
mono_dense_keras-0.1.1.dist-info/entry_points.txt
mono_dense_keras-0.1.1.dist-info/top_level.txt
mono_dense_keras-0.1.1.dist-info/RECORD
