Metadata-Version: 2.4
Name: mono-dense-keras
Version: 0.1.1
Summary: Monotonic Dense Layer implemented in Keras
Home-page: https://github.com/airtai/mono-dense-keras
Author: AIRT Technologies d.o.o.
Author-email: info@airt.ai
License: Creative Commons License
Project-URL: Bug Tracker, https://github.com/airtai/mono-dense-keras/issues
Project-URL: CI, https://github.com/airtai/mono-dense-keras/actions
Project-URL: Documentation, https://mono-dense-keras.airt.ai/
Keywords: tensorflow monotone monotonic dense layer nbdev nbdev-mkdocs jupyter notebook python
Classifier: Development Status :: 5 - Production/Stable
Classifier: Intended Audience :: Developers
Classifier: Natural Language :: English
Classifier: Programming Language :: Python :: 3.8
Classifier: Programming Language :: Python :: 3.9
Classifier: Programming Language :: Python :: 3.10
Classifier: Programming Language :: Python :: 3.11
Classifier: License :: Free for non-commercial use
Requires-Python: >=3.8
License-File: LICENSE
Requires-Dist: tensorflow<2.16,>=2.10.0
Provides-Extra: dev
Requires-Dist: keras-tuner[bayesian]==1.3.5; extra == "dev"
Requires-Dist: nbdev-mkdocs==0.6.1; extra == "dev"
Requires-Dist: nbdev==2.3.12; extra == "dev"
Requires-Dist: fastcore==1.7.20; extra == "dev"
Requires-Dist: pytest==7.3.1; extra == "dev"
Requires-Dist: pandas>=1.3.5; extra == "dev"
Requires-Dist: nbqa==1.7.0; extra == "dev"
Requires-Dist: black==23.3.0; extra == "dev"
Requires-Dist: isort==5.12.0; extra == "dev"
Requires-Dist: matplotlib==3.7.1; extra == "dev"
Requires-Dist: seaborn==0.12.2; extra == "dev"
Requires-Dist: mypy==1.3.0; extra == "dev"
Requires-Dist: bandit==1.7.5; extra == "dev"
Requires-Dist: semgrep==1.23.0; extra == "dev"
Requires-Dist: tqdm; extra == "dev"
Dynamic: author
Dynamic: author-email
Dynamic: classifier
Dynamic: description
Dynamic: description-content-type
Dynamic: home-page
Dynamic: keywords
Dynamic: license
Dynamic: license-file
Dynamic: project-url
Dynamic: provides-extra
Dynamic: requires-dist
Dynamic: requires-python
Dynamic: summary
